I2C_TMP_final/I2C_TMP_final.ip_user_files/ip/ila_0/ila_0_stub.vhdl
-- Copyright 1986-2020 Xilinx, Inc. All Rights Reserved.
-- --------------------------------------------------------------------------------
-- Tool Version: Vivado v.2020.1 (win64) Build 2902540 Wed May 27 19:54:49 MDT 2020
-- Date        : Fri May 30 14:21:30 2025
-- Host        : Laptop_Umang running 64-bit major release  (build 9200)
-- Command     : write_vhdl -force -mode synth_stub
--               c:/Xilinx_Vitis/Projects/Zybo_Verilog/I2C_TMP_final/I2C_TMP_final.srcs/sources_1/ip/ila_0_1/ila_0_stub.vhdl
-- Design      : ila_0
-- Purpose     : Stub declaration of top-level module interface
-- Device      : xc7z010clg400-1
-- --------------------------------------------------------------------------------
library IEEE;
use IEEE.STD_LOGIC_1164.ALL;

entity ila_0 is
  Port ( 
    clk : in STD_LOGIC;
    probe0 : in STD_LOGIC_VECTOR ( 0 to 0 );
    probe1 : in STD_LOGIC_VECTOR ( 0 to 0 );
    probe2 : in STD_LOGIC_VECTOR ( 0 to 0 );
    probe3 : in STD_LOGIC_VECTOR ( 7 downto 0 );
    probe4 : in STD_LOGIC_VECTOR ( 7 downto 0 );
    probe5 : in STD_LOGIC_VECTOR ( 0 to 0 );
    probe6 : in STD_LOGIC_VECTOR ( 4 downto 0 );
    probe7 : in STD_LOGIC_VECTOR ( 7 downto 0 );
    probe8 : in STD_LOGIC_VECTOR ( 2 downto 0 );
    probe9 : in STD_LOGIC_VECTOR ( 0 to 0 );
    probe10 : in STD_LOGIC_VECTOR ( 0 to 0 );
    probe11 : in STD_LOGIC_VECTOR ( 0 to 0 );
    probe12 : in STD_LOGIC_VECTOR ( 0 to 0 )
  );

end ila_0;

architecture stub of ila_0 is
attribute syn_black_box : boolean;
attribute black_box_pad_pin : string;
attribute syn_black_box of stub : architecture is true;
attribute black_box_pad_pin of stub : architecture is "clk,probe0[0:0],probe1[0:0],probe2[0:0],probe3[7:0],probe4[7:0],probe5[0:0],probe6[4:0],probe7[7:0],probe8[2:0],probe9[0:0],probe10[0:0],probe11[0:0],probe12[0:0]";
attribute X_CORE_INFO : string;
attribute X_CORE_INFO of stub : architecture is "ila,Vivado 2020.1";
begin
end;

I2C_TMP_final/I2C_TMP_final.srcs/sources_1/new/i2c_tmp.v
`timescale 1ns / 1ps

module i2c_tmp3_fsm (
    input wire clk,
    input wire rst,
    inout wire sda,
    output reg scl,
    //output [3:0]leds 
    output reg [7:0] temp_msb,
    output reg [7:0] temp_lsb,
    output reg done
);

    parameter SLAVE_ADDR = 7'b1001000;
    parameter REG_TEMP   = 8'h00;

    parameter IDLE = 5'd0, START = 5'd1, ADDR_L = 5'd2, ADDR_H = 5'd3, ACK_ADDR_L = 5'd4,
              ACK_ADDR_H = 5'd5, PTR_L = 5'd6, PTR_H = 5'd7, ACK_PTR_L = 5'd8, ACK_PTR_H = 5'd9,
              MSB_L = 5'd10, MSB_H = 5'd11, M_ACK_L = 5'd12, M_ACK_H = 5'd13, LSB_L = 5'd14, LSB_H = 5'd15, STOP = 5'd16;
    
//    reg [7:0] temp_msb;
//   reg [7:0] temp_lsb;
//    reg done;
    
    reg [4:0] state;
    reg [7:0] shift_reg;
    reg [2:0] bit_cnt;
    reg [15:0] clk_div;
    reg i2c_clk_en;
    reg read_en;
    reg sda_out;
    reg sda_oe;
    reg pass2 = 0;

    assign sda = sda_oe ? sda_out : 1'bz;
//    assign leds[0] = temp_lsb[0];
//    assign leds[1] = temp_lsb[1];
//    assign leds[2] = temp_lsb[2];
//    assign leds[3] = temp_lsb[3];

ila_0 ila_i (
	.clk(clk), // input wire clk


	.probe0(rst), // input wire [0:0]  probe0  
	.probe1(sda), // input wire [0:0]  probe1 
	.probe2(scl), // input wire [0:0]  probe2 
	.probe3(temp_msb), // input wire [7:0]  probe3 
	.probe4(temp_lsb), // input wire [7:0]  probe4 
	.probe5(done), // input wire [0:0]  probe5 
	.probe6(state), // input wire [4:0]  probe6 
	.probe7(shift_reg), // input wire [7:0]  probe7 
	.probe8(bit_cnt), // input wire [2:0]  probe8 
	.probe9(i2c_clk_en), // input wire [0:0]  probe9 
	.probe10(read_en), // input wire [0:0]  probe10 
	.probe11(sda_out), // input wire [0:0]  probe11 
	.probe12(sda_oe) // input wire [0:0]  probe12
);
   
    
    always @(posedge clk or posedge rst) begin
        if (rst) begin
            clk_div <= 0;
            i2c_clk_en <= 0;
        end else begin
            if (clk_div == 256) begin //Clock Divider
                clk_div <= 0;
                i2c_clk_en <= 1;
            end else begin
                clk_div <= clk_div + 1;
                i2c_clk_en <= 0;
            end
        end
    end

    always @(posedge clk) begin
        if (rst) begin
            state <= IDLE;
            scl <= 1;
            sda_out <= 1'b1;
            sda_oe <= 1;
            done <= 0;
            bit_cnt <= 7;
        end else if (i2c_clk_en) begin
            case (state)
                IDLE: begin
                    scl <= 1; sda_out <= 1; sda_oe <= 1;
                    done <= 0;
                    if(!pass2) begin
                        read_en <= 0;
                        pass2 = 1;
                    end else begin
                        read_en <=1;
                    end
                    state <= START;
                end

                START: begin
                    sda_out <= 0;
                    shift_reg <= {SLAVE_ADDR, read_en};
                    bit_cnt <= 7;
                    state <= ADDR_L;
                end

                ADDR_L: begin
                    sda_oe <= 1;
                    scl <= 0;
                    sda_out <= shift_reg[bit_cnt];
                    state <= ADDR_H;
                end

                ADDR_H: begin
                    scl <= 1;
                    if (bit_cnt == 0)begin
                     state <= ACK_ADDR_L;
                     bit_cnt <= 7;
                    end
                    else begin 
                        bit_cnt <= bit_cnt - 1; 
                        state <= ADDR_L; 
                    end
                end

                ACK_ADDR_L: begin scl <= 0; sda_oe <= 0; state <= ACK_ADDR_H; end
                ACK_ADDR_H: begin 
                    scl <= 1; 
                    if(sda == 0 && read_en == 0) begin
                        state <= PTR_L; 
                        bit_cnt <= 7; 
                        shift_reg <= REG_TEMP; 
                    end else if(sda == 0 && read_en == 1) begin
                        state <= MSB_L;
                    end
                end

                PTR_L: begin scl <= 0; sda_oe <= 1; sda_out <= shift_reg[bit_cnt]; state <= PTR_H; end
                PTR_H: begin scl <= 1;
                    if (bit_cnt == 0) begin 
                        state <= ACK_PTR_L;
                        bit_cnt <= 7;
                    end
                    else begin bit_cnt <= bit_cnt - 1; state <= PTR_L; end
                end

                ACK_PTR_L: begin scl <= 0; sda_oe <= 0;read_en <= 1; state <= ACK_PTR_H; end
                ACK_PTR_H: begin 
                    scl <= 1;
                    if(sda == 0)begin
                        state <= IDLE;
                        bit_cnt <= 7;
                        shift_reg <= {SLAVE_ADDR, read_en};
                    end else state <= STOP;
                end

                

                MSB_L: begin scl <= 0; sda_oe<=0; state <= MSB_H; end
                MSB_H: begin 
                    scl <= 1; 
                    temp_msb[bit_cnt] <= sda;
                    if (bit_cnt == 0) begin
                        state <= M_ACK_L;
                        sda_oe <= 1;
                        bit_cnt <= 7;
                    end
                    else begin bit_cnt <= bit_cnt - 1; state <= MSB_L; end
                end

                M_ACK_L: begin 
                    scl <= 0; 
                    if(temp_msb != 0)begin
                        sda_out <= 0; 
                        state <= M_ACK_H; 
                    end else begin
                        state <= IDLE;
                    end
                end
                M_ACK_H: begin scl <= 1; state <= LSB_L; bit_cnt <= 7; end

                LSB_L: begin scl <= 0; sda_oe <= 0; state <= LSB_H; end
                LSB_H: begin scl <= 1; temp_lsb[bit_cnt] <= sda;
                    if (bit_cnt == 0) state <= STOP;
                    else begin bit_cnt <= bit_cnt - 1; state <= LSB_L; end
                end

                STOP: begin scl <= 1; sda_oe <= 1; sda_out <= 0; sda_out <= 1; done <= 1; end

                default: state <= IDLE;
            endcase
        end
    end

endmodule

I2C_TMP_final/I2C_TMP_final.srcs/sim_1/new/tb.v
`timescale 1ns / 1ps

module tb_i2c_tmp3_fsm;

    reg clk;
    reg rst;
    wire sda;
    wire scl;
    wire [7:0] temp_msb;
    wire [7:0] temp_lsb;
    wire done;
    
    wire [4:0] state;
    wire [7:0] shift_reg;
    wire [2:0] bit_cnt;
    wire i2c_clk_en;
    wire read_en;
    wire sda_out;
    wire sda_oe;
    
    reg sda_slave_drive;
    reg sda_slave_oe;

    assign sda = (!dut.sda_oe) ? 1'b0 : 1'bz;
    assign state = dut.state;
    assign shift_reg = dut.shift_reg;
    assign bit_cnt = dut.bit_cnt;
    assign i2c_clk_en = dut.i2c_clk_en;
    assign read_en = dut.read_en;
    assign sda_out = dut.sda_out;
    assign sda_oe = dut.sda_oe;
    // Instantiate DUT
    i2c_tmp3_fsm dut (
        .clk(clk),
        .rst(rst),
        .sda(sda),
        .scl(scl),
        .temp_msb(temp_msb),
        .temp_lsb(temp_lsb),
        .done(done)
    );

    // Clock generation
    initial begin
        clk = 0;
        forever #4 clk = ~clk;  // 125 MHz -> 8 ns period
    end
    
    // Stimulus
    initial begin
        rst = 1;
        sda_slave_drive = 1;
        sda_slave_oe = 0;
        #20;
        rst = 0;

        // Simulate slave ACKs and data (simple example)
        forever begin
            @(negedge scl);
            if (dut.sda_oe == 0) begin
                // Master is reading, we provide data
                sda_slave_oe = 1;
                sda_slave_drive = 0;  // provide random bit
            end else begin
                sda_slave_oe = 0;  // release line when master drives
            end
        end
    end

    // Monitor
    initial begin
        $dumpfile("i2c_tmp3_fsm_tb.vcd");
        $dumpvars(0, tb_i2c_tmp3_fsm);
        $dumpvars(0, dut.i2c_clk_en);  // add i2c_clk_en signal to waveform
        #150_000 $finish;
    end

endmodule

I2C_TMP_final/I2C_TMP_final.sim/sim_1/behav/xsim/i2c_tmp3_fsm_tb.vcd
$date
   Mon Jun  2 22:39:35 2025
$end
$version
  2020.1
$end
$timescale
  1ps
$end
$scope module tb_i2c_tmp3_fsm $end
$var reg 1 ! clk $end
$var reg 1 " rst $end
$var wire 1 # sda $end
$var wire 1 $ scl $end
$var wire 8 % temp_msb [7:0] $end
$var wire 8 & temp_lsb [7:0] $end
$var wire 1 ' done $end
$var wire 5 ( state [4:0] $end
$var wire 8 ) shift_reg [7:0] $end
$var wire 3 * bit_cnt [2:0] $end
$var wire 1 + i2c_clk_en $end
$var wire 1 , read_en $end
$var wire 1 - sda_out $end
$var wire 1 . sda_oe $end
$var reg 1 / sda_slave_drive $end
$var reg 1 0 sda_slave_oe $end
$scope module dut $end
$var wire 1 1 clk $end
$var wire 1 2 rst $end
$var wire 1 # sda $end
$var reg 1 3 scl $end
$var reg 8 4 temp_msb [7:0] $end
$var reg 8 5 temp_lsb [7:0] $end
$var reg 1 6 done $end
$var reg 5 7 state [4:0] $end
$var reg 8 8 shift_reg [7:0] $end
$var reg 3 9 bit_cnt [2:0] $end
$var reg 16 : clk_div [15:0] $end
$var reg 1 ; i2c_clk_en $end
$var reg 1 < read_en $end
$var reg 1 = sda_out $end
$var reg 1 > sda_oe $end
$var reg 1 ? pass2 $end
$var parameter 7 @ SLAVE_ADDR [6:0] $end
$var parameter 8 A REG_TEMP [7:0] $end
$var parameter 5 B IDLE [4:0] $end
$var parameter 5 C START [4:0] $end
$var parameter 5 D ADDR_L [4:0] $end
$var parameter 5 E ADDR_H [4:0] $end
$var parameter 5 F ACK_ADDR_L [4:0] $end
$var parameter 5 G ACK_ADDR_H [4:0] $end
$var parameter 5 H PTR_L [4:0] $end
$var parameter 5 I PTR_H [4:0] $end
$var parameter 5 J ACK_PTR_L [4:0] $end
$var parameter 5 K ACK_PTR_H [4:0] $end
$var parameter 5 L MSB_L [4:0] $end
$var parameter 5 M MSB_H [4:0] $end
$var parameter 5 N M_ACK_L [4:0] $end
$var parameter 5 O M_ACK_H [4:0] $end
$var parameter 5 P LSB_L [4:0] $end
$var parameter 5 Q LSB_H [4:0] $end
$var parameter 5 R STOP [4:0] $end
$scope module ila_i $end
$var wire 1 1 clk $end
$var wire 1 2 probe0 [0:0] $end
$var wire 1 # probe1 [0:0] $end
$var wire 1 3 probe2 [0:0] $end
$var wire 8 4 probe3 [7:0] $end
$var wire 8 5 probe4 [7:0] $end
$var wire 1 6 probe5 [0:0] $end
$var wire 5 S probe6 [4:0] $end
$var wire 8 T probe7 [7:0] $end
$var wire 3 U probe8 [2:0] $end
$var wire 1 V probe9 [0:0] $end
$var wire 1 W probe10 [0:0] $end
$var wire 1 X probe11 [0:0] $end
$var wire 1 Y probe12 [0:0] $end
$upscope $end
$upscope $end
$upscope $end
$enddefinitions $end
#0
$dumpvars
0!
1"
x#
x$
bx %
bx &
x'
bx (
bx )
bx *
0+
x,
x-
x.
1/
00
01
12
x3
bx 4
bx 5
x6
bx 7
bx 8
bx 9
b0 :
0;
x<
x=
x>
0?
b1001000 @
b0 A
b0 B
b1 C
b10 D
b11 E
b100 F
b101 G
b110 H
b111 I
b1000 J
b1001 K
b1010 L
b1011 M
b1100 N
b1101 O
b1110 P
b1111 Q
b10000 R
bx S
bx T
bx U
0V
xW
xX
xY
$end
#4000
1!
1#
1$
0'
b0 (
b111 *
1-
1.
11
13
06
b0 7
b111 9
0;
1=
1>
b0 S
b111 U
1X
1Y
#8000
0!
01
#12000
1!
11
0;
#16000
0!
01
#20000
1!
0"
11
02
b1 :
0;
#24000
0!
01
#28000
1!
11
b10 :
0;
#32000
0!
01
#36000
1!
11
b11 :
0;
#40000
0!
01
#44000
1!
11
b100 :
0;
#48000
0!
01
#52000
1!
11
b101 :
0;
#56000
0!
01
#60000
1!
11
b110 :
0;
#64000
0!
01
#68000
1!
11
b111 :
0;
#72000
0!
01
#76000
1!
11
b1000 :
0;
#80000
0!
01
#84000
1!
11
b1001 :
0;
#88000
0!
01
#92000
1!
11
b1010 :
0;
#96000
0!
01
#100000
1!
11
b1011 :
0;
#104000
0!
01
#108000
1!
11
b1100 :
0;
#112000
0!
01
#116000
1!
11
b1101 :
0;
#120000
0!
01
#124000
1!
11
b1110 :
0;
#128000
0!
01
#132000
1!
11
b1111 :
0;
#136000
0!
01
#140000
1!
11
b10000 :
0;
#144000
0!
01
#148000
1!
11
b10001 :
0;
#152000
0!
01
#156000
1!
11
b10010 :
0;
#160000
0!
01
#164000
1!
11
b10011 :
0;
#168000
0!
01
#172000
1!
11
b10100 :
0;
#176000
0!
01
#180000
1!
11
b10101 :
0;
#184000
0!
01
#188000
1!
11
b10110 :
0;
#192000
0!
01
#196000
1!
11
b10111 :
0;
#200000
0!
01
#204000
1!
11
b11000 :
0;
#208000
0!
01
#212000
1!
11
b11001 :
0;
#216000
0!
01
#220000
1!
11
b11010 :
0;
#224000
0!
01
#228000
1!
11
b11011 :
0;
#232000
0!
01
#236000
1!
11
b11100 :
0;
#240000
0!
01
#244000
1!
11
b11101 :
0;
#248000
0!
01
#252000
1!
11
b11110 :
0;
#256000
0!
01
#260000
1!
11
b11111 :
0;
#264000
0!
01
#268000
1!
11
b100000 :
0;
#272000
0!
01
#276000
1!
11
b100001 :
0;
#280000
0!
01
#284000
1!
11
b100010 :
0;
#288000
0!
01
#292000
1!
11
b100011 :
0;
#296000
0!
01
#300000
1!
11
b100100 :
0;
#304000
0!
01
#308000
1!
11
b100101 :
0;
#312000
0!
01
#316000
1!
11
b100110 :
0;
#320000
0!
01
#324000
1!
11
b100111 :
0;
#328000
0!
01
#332000
1!
11
b101000 :
0;
#336000
0!
01
#340000
1!
11
b101001 :
0;
#344000
0!
01
#348000
1!
11
b101010 :
0;
#352000
0!
01
#356000
1!
11
b101011 :
0;
#360000
0!
01
#364000
1!
11
b101100 :
0;
#368000
0!
01
#372000
1!
11
b101101 :
0;
#376000
0!
01
#380000
1!
11
b101110 :
0;
#384000
0!
01
#388000
1!
11
b101111 :
0;
#392000
0!
01
#396000
1!
11
b110000 :
0;
#400000
0!
01
#404000
1!
11
b110001 :
0;
#408000
0!
01
#412000
1!
11
b110010 :
0;
#416000
0!
01
#420000
1!
11
b110011 :
0;
#424000
0!
01
#428000
1!
11
b110100 :
0;
#432000
0!
01
#436000
1!
11
b110101 :
0;
#440000
0!
01
#444000
1!
11
b110110 :
0;
#448000
0!
01
#452000
1!
11
b110111 :
0;
#456000
0!
01
#460000
1!
11
b111000 :
0;
#464000
0!
01
#468000
1!
11
b111001 :
0;
#472000
0!
01
#476000
1!
11
b111010 :
0;
#480000
0!
01
#484000
1!
11
b111011 :
0;
#488000
0!
01
#492000
1!
11
b111100 :
0;
#496000
0!
01
#500000
1!
11
b111101 :
0;
#504000
0!
01
#508000
1!
11
b111110 :
0;
#512000
0!
01
#516000
1!
11
b111111 :
0;
#520000
0!
01
#524000
1!
11
b1000000 :
0;
#528000
0!
01
#532000
1!
11
b1000001 :
0;
#536000
0!
01
#540000
1!
11
b1000010 :
0;
#544000
0!
01
#548000
1!
11
b1000011 :
0;
#552000
0!
01
#556000
1!
11
b1000100 :
0;
#560000
0!
01
#564000
1!
11
b1000101 :
0;
#568000
0!
01
#572000
1!
11
b1000110 :
0;
#576000
0!
01
#580000
1!
11
b1000111 :
0;
#584000
0!
01
#588000
1!
11
b1001000 :
0;
#592000
0!
01
#596000
1!
11
b1001001 :
0;
#600000
0!
01
#604000
1!
11
b1001010 :
0;
#608000
0!
01
#612000
1!
11
b1001011 :
0;
#616000
0!
01
#620000
1!
11
b1001100 :
0;
#624000
0!
01
#628000
1!
11
b1001101 :
0;
#632000
0!
01
#636000
1!
11
b1001110 :
0;
#640000
0!
01
#644000
1!
11
b1001111 :
0;
#648000
0!
01
#652000
1!
11
b1010000 :
0;
#656000
0!
01
#660000
1!
11
b1010001 :
0;
#664000
0!
01
#668000
1!
11
b1010010 :
0;
#672000
0!
01
#676000
1!
11
b1010011 :
0;
#680000
0!
01
#684000
1!
11
b1010100 :
0;
#688000
0!
01
#692000
1!
11
b1010101 :
0;
#696000
0!
01
#700000
1!
11
b1010110 :
0;
#704000
0!
01
#708000
1!
11
b1010111 :
0;
#712000
0!
01
#716000
1!
11
b1011000 :
0;
#720000
0!
01
#724000
1!
11
b1011001 :
0;
#728000
0!
01
#732000
1!
11
b1011010 :
0;
#736000
0!
01
#740000
1!
11
b1011011 :
0;
#744000
0!
01
#748000
1!
11
b1011100 :
0;
#752000
0!
01
#756000
1!
11
b1011101 :
0;
#760000
0!
01
#764000
1!
11
b1011110 :
0;
#768000
0!
01
#772000
1!
11
b1011111 :
0;
#776000
0!
01
#780000
1!
11
b1100000 :
0;
#784000
0!
01
#788000
1!
11
b1100001 :
0;
#792000
0!
01
#796000
1!
11
b1100010 :
0;
#800000
0!
01
#804000
1!
11
b1100011 :
0;
#808000
0!
01
#812000
1!
11
b1100100 :
0;
#816000
0!
01
#820000
1!
11
b1100101 :
0;
#824000
0!
01
#828000
1!
11
b1100110 :
0;
#832000
0!
01
#836000
1!
11
b1100111 :
0;
#840000
0!
01
#844000
1!
11
b1101000 :
0;
#848000
0!
01
#852000
1!
11
b1101001 :
0;
#856000
0!
01
#860000
1!
11
b1101010 :
0;
#864000
0!
01
#868000
1!
11
b1101011 :
0;
#872000
0!
01
#876000
1!
11
b1101100 :
0;
#880000
0!
01
#884000
1!
11
b1101101 :
0;
#888000
0!
01
#892000
1!
11
b1101110 :
0;
#896000
0!
01
#900000
1!
11
b1101111 :
0;
#904000
0!
01
#908000
1!
11
b1110000 :
0;
#912000
0!
01
#916000
1!
11
b1110001 :
0;
#920000
0!
01
#924000
1!
11
b1110010 :
0;
#928000
0!
01
#932000
1!
11
b1110011 :
0;
#936000
0!
01
#940000
1!
11
b1110100 :
0;
#944000
0!
01
#948000
1!
11
b1110101 :
0;
#952000
0!
01
#956000
1!
11
b1110110 :
0;
#960000
0!
01
#964000
1!
11
b1110111 :
0;
#968000
0!
01
#972000
1!
11
b1111000 :
0;
#976000
0!
01
#980000
1!
11
b1111001 :
0;
#984000
0!
01
#988000
1!
11
b1111010 :
0;
#992000
0!
01
#996000
1!
11
b1111011 :
0;
#1000000
0!
01
#1004000
1!
11
b1111100 :
0;
#1008000
0!
01
#1012000
1!
11
b1111101 :
0;
#1016000
0!
01
#1020000
1!
11
b1111110 :
0;
#1024000
0!
01
#1028000
1!
11
b1111111 :
0;
#1032000
0!
01
#1036000
1!
11
b10000000 :
0;
#1040000
0!
01
#1044000
1!
11
b10000001 :
0;
#1048000
0!
01
#1052000
1!
11
b10000010 :
0;
#1056000
0!
01
#1060000
1!
11
b10000011 :
0;
#1064000
0!
01
#1068000
1!
11
b10000100 :
0;
#1072000
0!
01
#1076000
1!
11
b10000101 :
0;
#1080000
0!
01
#1084000
1!
11
b10000110 :
0;
#1088000
0!
01
#1092000
1!
11
b10000111 :
0;
#1096000
0!
01
#1100000
1!
11
b10001000 :
0;
#1104000
0!
01
#1108000
1!
11
b10001001 :
0;
#1112000
0!
01
#1116000
1!
11
b10001010 :
0;
#1120000
0!
01
#1124000
1!
11
b10001011 :
0;
#1128000
0!
01
#1132000
1!
11
b10001100 :
0;
#1136000
0!
01
#1140000
1!
11
b10001101 :
0;
#1144000
0!
01
#1148000
1!
11
b10001110 :
0;
#1152000
0!
01
#1156000
1!
11
b10001111 :
0;
#1160000
0!
01
#1164000
1!
11
b10010000 :
0;
#1168000
0!
01
#1172000
1!
11
b10010001 :
0;
#1176000
0!
01
#1180000
1!
11
b10010010 :
0;
#1184000
0!
01
#1188000
1!
11
b10010011 :
0;
#1192000
0!
01
#1196000
1!
11
b10010100 :
0;
#1200000
0!
01
#1204000
1!
11
b10010101 :
0;
#1208000
0!
01
#1212000
1!
11
b10010110 :
0;
#1216000
0!
01
#1220000
1!
11
b10010111 :
0;
#1224000
0!
01
#1228000
1!
11
b10011000 :
0;
#1232000
0!
01
#1236000
1!
11
b10011001 :
0;
#1240000
0!
01
#1244000
1!
11
b10011010 :
0;
#1248000
0!
01
#1252000
1!
11
b10011011 :
0;
#1256000
0!
01
#1260000
1!
11
b10011100 :
0;
#1264000
0!
01
#1268000
1!
11
b10011101 :
0;
#1272000
0!
01
#1276000
1!
11
b10011110 :
0;
#1280000
0!
01
#1284000
1!
11
b10011111 :
0;
#1288000
0!
01
#1292000
1!
11
b10100000 :
0;
#1296000
0!
01
#1300000
1!
11
b10100001 :
0;
#1304000
0!
01
#1308000
1!
11
b10100010 :
0;
#1312000
0!
01
#1316000
1!
11
b10100011 :
0;
#1320000
0!
01
#1324000
1!
11
b10100100 :
0;
#1328000
0!
01
#1332000
1!
11
b10100101 :
0;
#1336000
0!
01
#1340000
1!
11
b10100110 :
0;
#1344000
0!
01
#1348000
1!
11
b10100111 :
0;
#1352000
0!
01
#1356000
1!
11
b10101000 :
0;
#1360000
0!
01
#1364000
1!
11
b10101001 :
0;
#1368000
0!
01
#1372000
1!
11
b10101010 :
0;
#1376000
0!
01
#1380000
1!
11
b10101011 :
0;
#1384000
0!
01
#1388000
1!
11
b10101100 :
0;
#1392000
0!
01
#1396000
1!
11
b10101101 :
0;
#1400000
0!
01
#1404000
1!
11
b10101110 :
0;
#1408000
0!
01
#1412000
1!
11
b10101111 :
0;
#1416000
0!
01
#1420000
1!
11
b10110000 :
0;
#1424000
0!
01
#1428000
1!
11
b10110001 :
0;
#1432000
0!
01
#1436000
1!
11
b10110010 :
0;
#1440000
0!
01
#1444000
1!
11
b10110011 :
0;
#1448000
0!
01
#1452000
1!
11
b10110100 :
0;
#1456000
0!
01
#1460000
1!
11
b10110101 :
0;
#1464000
0!
01
#1468000
1!
11
b10110110 :
0;
#1472000
0!
01
#1476000
1!
11
b10110111 :
0;
#1480000
0!
01
#1484000
1!
11
b10111000 :
0;
#1488000
0!
01
#1492000
1!
11
b10111001 :
0;
#1496000
0!
01
#1500000
1!
11
b10111010 :
0;
#1504000
0!
01
#1508000
1!
11
b10111011 :
0;
#1512000
0!
01
#1516000
1!
11
b10111100 :
0;
#1520000
0!
01
#1524000
1!
11
b10111101 :
0;
#1528000
0!
01
#1532000
1!
11
b10111110 :
0;
#1536000
0!
01
#1540000
1!
11
b10111111 :
0;
#1544000
0!
01
#1548000
1!
11
b11000000 :
0;
#1552000
0!
01
#1556000
1!
11
b11000001 :
0;
#1560000
0!
01
#1564000
1!
11
b11000010 :
0;
#1568000
0!
01
#1572000
1!
11
b11000011 :
0;
#1576000
0!
01
#1580000
1!
11
b11000100 :
0;
#1584000
0!
01
#1588000
1!
11
b11000101 :
0;
#1592000
0!
01
#1596000
1!
11
b11000110 :
0;
#1600000
0!
01
#1604000
1!
11
b11000111 :
0;
#1608000
0!
01
#1612000
1!
11
b11001000 :
0;
#1616000
0!
01
#1620000
1!
11
b11001001 :
0;
#1624000
0!
01
#1628000
1!
11
b11001010 :
0;
#1632000
0!
01
#1636000
1!
11
b11001011 :
0;
#1640000
0!
01
#1644000
1!
11
b11001100 :
0;
#1648000
0!
01
#1652000
1!
11
b11001101 :
0;
#1656000
0!
01
#1660000
1!
11
b11001110 :
0;
#1664000
0!
01
#1668000
1!
11
b11001111 :
0;
#1672000
0!
01
#1676000
1!
11
b11010000 :
0;
#1680000
0!
01
#1684000
1!
11
b11010001 :
0;
#1688000
0!
01
#1692000
1!
11
b11010010 :
0;
#1696000
0!
01
#1700000
1!
11
b11010011 :
0;
#1704000
0!
01
#1708000
1!
11
b11010100 :
0;
#1712000
0!
01
#1716000
1!
11
b11010101 :
0;
#1720000
0!
01
#1724000
1!
11
b11010110 :
0;
#1728000
0!
01
#1732000
1!
11
b11010111 :
0;
#1736000
0!
01
#1740000
1!
11
b11011000 :
0;
#1744000
0!
01
#1748000
1!
11
b11011001 :
0;
#1752000
0!
01
#1756000
1!
11
b11011010 :
0;
#1760000
0!
01
#1764000
1!
11
b11011011 :
0;
#1768000
0!
01
#1772000
1!
11
b11011100 :
0;
#1776000
0!
01
#1780000
1!
11
b11011101 :
0;
#1784000
0!
01
#1788000
1!
11
b11011110 :
0;
#1792000
0!
01
#1796000
1!
11
b11011111 :
0;
#1800000
0!
01
#1804000
1!
11
b11100000 :
0;
#1808000
0!
01
#1812000
1!
11
b11100001 :
0;
#1816000
0!
01
#1820000
1!
11
b11100010 :
0;
#1824000
0!
01
#1828000
1!
11
b11100011 :
0;
#1832000
0!
01
#1836000
1!
11
b11100100 :
0;
#1840000
0!
01
#1844000
1!
11
b11100101 :
0;
#1848000
0!
01
#1852000
1!
11
b11100110 :
0;
#1856000
0!
01
#1860000
1!
11
b11100111 :
0;
#1864000
0!
01
#1868000
1!
11
b11101000 :
0;
#1872000
0!
01
#1876000
1!
11
b11101001 :
0;
#1880000
0!
01
#1884000
1!
11
b11101010 :
0;
#1888000
0!
01
#1892000
1!
11
b11101011 :
0;
#1896000
0!
01
#1900000
1!
11
b11101100 :
0;
#1904000
0!
01
#1908000
1!
11
b11101101 :
0;
#1912000
0!
01
#1916000
1!
11
b11101110 :
0;
#1920000
0!
01
#1924000
1!
11
b11101111 :
0;
#1928000
0!
01
#1932000
1!
11
b11110000 :
0;
#1936000
0!
01
#1940000
1!
11
b11110001 :
0;
#1944000
0!
01
#1948000
1!
11
b11110010 :
0;
#1952000
0!
01
#1956000
1!
11
b11110011 :
0;
#1960000
0!
01
#1964000
1!
11
b11110100 :
0;
#1968000
0!
01
#1972000
1!
11
b11110101 :
0;
#1976000
0!
01
#1980000
1!
11
b11110110 :
0;
#1984000
0!
01
#1988000
1!
11
b11110111 :
0;
#1992000
0!
01
#1996000
1!
11
b11111000 :
0;
#2000000
0!
01
#2004000
1!
11
b11111001 :
0;
#2008000
0!
01
#2012000
1!
11
b11111010 :
0;
#2016000
0!
01
#2020000
1!
11
b11111011 :
0;
#2024000
0!
01
#2028000
1!
11
b11111100 :
0;
#2032000
0!
01
#2036000
1!
11
b11111101 :
0;
#2040000
0!
01
#2044000
1!
11
b11111110 :
0;
#2048000
0!
01
#2052000
1!
11
b11111111 :
0;
#2056000
0!
01
#2060000
1!
11
b100000000 :
0;
#2064000
0!
01
#2068000
1!
1+
11
b0 :
1;
1V
#2072000
0!
01
#2076000
1!
b1 (
0+
0,
11
b1 7
b1 :
0;
0<
1?
b1 S
0V
0W
#2080000
0!
01
#2084000
1!
11
b10 :
0;
#2088000
0!
01
#2092000
1!
11
b11 :
0;
#2096000
0!
01
#2100000
1!
11
b100 :
0;
#2104000
0!
01
#2108000
1!
11
b101 :
0;
#2112000
0!
01
#2116000
1!
11
b110 :
0;
#2120000
0!
01
#2124000
1!
11
b111 :
0;
#2128000
0!
01
#2132000
1!
11
b1000 :
0;
#2136000
0!
01
#2140000
1!
11
b1001 :
0;
#2144000
0!
01
#2148000
1!
11
b1010 :
0;
#2152000
0!
01
#2156000
1!
11
b1011 :
0;
#2160000
0!
01
#2164000
1!
11
b1100 :
0;
#2168000
0!
01
#2172000
1!
11
b1101 :
0;
#2176000
0!
01
#2180000
1!
11
b1110 :
0;
#2184000
0!
01
#2188000
1!
11
b1111 :
0;
#2192000
0!
01
#2196000
1!
11
b10000 :
0;
#2200000
0!
01
#2204000
1!
11
b10001 :
0;
#2208000
0!
01
#2212000
1!
11
b10010 :
0;
#2216000
0!
01
#2220000
1!
11
b10011 :
0;
#2224000
0!
01
#2228000
1!
11
b10100 :
0;
#2232000
0!
01
#2236000
1!
11
b10101 :
0;
#2240000
0!
01
#2244000
1!
11
b10110 :
0;
#2248000
0!
01
#2252000
1!
11
b10111 :
0;
#2256000
0!
01
#2260000
1!
11
b11000 :
0;
#2264000
0!
01
#2268000
1!
11
b11001 :
0;
#2272000
0!
01
#2276000
1!
11
b11010 :
0;
#2280000
0!
01
#2284000
1!
11
b11011 :
0;
#2288000
0!
01
#2292000
1!
11
b11100 :
0;
#2296000
0!
01
#2300000
1!
11
b11101 :
0;
#2304000
0!
01
#2308000
1!
11
b11110 :
0;
#2312000
0!
01
#2316000
1!
11
b11111 :
0;
#2320000
0!
01
#2324000
1!
11
b100000 :
0;
#2328000
0!
01
#2332000
1!
11
b100001 :
0;
#2336000
0!
01
#2340000
1!
11
b100010 :
0;
#2344000
0!
01
#2348000
1!
11
b100011 :
0;
#2352000
0!
01
